{"cameraMode":{"drawMode":0,"name":"Shaded","section":"Shading Mode"},"sceneLighting":true,"audioPlay":false,"sceneViewState":{"m_AlwaysRefresh":true,"showFog":true,"showSkybox":true,"showFlares":true,"showImageEffects":true,"showParticleSystems":true,"showVisualEffectGraphs":true,"m_FxEnabled":true},"in2DMode":false,"pivot":{"x":5.281797409057617,"y":0.4136752486228943,"z":-4.725484848022461},"rotation":{"x":-0.15432488918304444,"y":0.8384091854095459,"z":-0.30444425344467165,"w":-0.42504191398620608},"size":3.248584508895874,"orthographic":false}